pypatconsole/__init__.py
pypatconsole/config.py
pypatconsole/consoleclass.py
pypatconsole/curses_interface.py
pypatconsole/funcmap.py
pypatconsole/simple_interface.py
pypatconsole/strings.py
pypatconsole/utils.py
pypatconsole-0.0.20.dist-info/LICENSE
pypatconsole-0.0.20.dist-info/METADATA
pypatconsole-0.0.20.dist-info/WHEEL
pypatconsole-0.0.20.dist-info/top_level.txt
pypatconsole-0.0.20.dist-info/RECORD
