Metadata-Version: 2.1
Name: pypatconsole
Version: 0.0.20
Summary: Simple and sexy console interface
Home-page: https://github.com/Napam/PyPat-Console
Author: Naphat Amundsen
Author-email: naphat@live.com
License: UNKNOWN
Platform: UNKNOWN
Classifier: Programming Language :: Python :: 3
Classifier: License :: OSI Approved :: MIT License
Classifier: Operating System :: OS Independent
Requires-Python: >=3.6
